livekit/plugins/openai_sse/__init__.py
livekit/plugins/openai_sse/tts.py
livekit/plugins/openai_sse/version.py
livekit_plugins_openai_sse_tts-0.1.0.dist-info/METADATA
livekit_plugins_openai_sse_tts-0.1.0.dist-info/WHEEL
livekit_plugins_openai_sse_tts-0.1.0.dist-info/RECORD
